dot_prop/__init__.py
dot_prop-0.2.0.dist-info/DESCRIPTION.rst
dot_prop-0.2.0.dist-info/METADATA
dot_prop-0.2.0.dist-info/RECORD
dot_prop-0.2.0.dist-info/WHEEL
dot_prop-0.2.0.dist-info/metadata.json
dot_prop-0.2.0.dist-info/top_level.txt
